datamonk/invest_tools/__init__.py
datamonk/invest_tools/sreality.py
datamonk_invest_tools-0.1.2.dist-info/WHEEL
datamonk_invest_tools-0.1.2.dist-info/METADATA
datamonk_invest_tools-0.1.2.dist-info/RECORD
